kaspad_client/__init__.py
kaspad_client/kaspa_grpc/__init__.py
kaspad_client/kaspa_grpc/messages_pb2.py
kaspad_client/kaspa_grpc/messages_pb2_grpc.py
kaspad_client/kaspa_grpc/protos/messages.proto
kaspad_client/kaspa_grpc/protos/rpc.proto
kaspad_client/kaspa_grpc/rpc_pb2.py
kaspad_client/kaspa_grpc/rpc_pb2_grpc.py
kaspad_client/modules/KaspadClient.py
kaspad_client/modules/KaspadStream.py
kaspad_client/modules/__init__.py
kaspad_client-1.0.6.dist-info/LICENSE
kaspad_client-1.0.6.dist-info/METADATA
kaspad_client-1.0.6.dist-info/WHEEL
kaspad_client-1.0.6.dist-info/RECORD
