Metadata-Version: 2.3
Name: kaspad_client
Version: 1.0.6
Summary: This is a simple gRPC client for a python application which communiactes with the Kaspa node called KASPAD. Note: This module is created for the RUST version and might be not compatible with the go written node.
Keywords: kaspa,kaspad,blockchain,blockdag,kas,grpc
Author: lAmeR1
Author-email: lamer1@github.com
Requires-Python: >=3.12,<4.0
Classifier: Programming Language :: Python :: 3
Classifier: Programming Language :: Python :: 3.12
Classifier: Programming Language :: Python :: 3.13
Requires-Dist: grpcio (>=1.62.1,<2.0.0)
Requires-Dist: protobuf (>=4.21.6,<5.0.0)
Project-URL: Homepage, https://kaspa.org/
Project-URL: Repository, https://github.com/lAmeR1/py-kaspad-client
